[{"name":"Yakuza","year":2005,"developer":"Amusement Vision, Ltd."},{"name":"Yakuza 2","year":2006,"developer":"Amusement Vision, Ltd."},{"name":"Yakuza Fury","year":2005,"developer":"Vingt et un Systems Corporation"},{"name":"Yanya Caballista: City Skater","year":2001,"developer":"CAVE Co., Ltd."},{"name":"Yatohime Zankikō: Tsurugi no Maki","year":2007,"developer":"Terios"},{"name":"Yetisports: Arctic Adventure","year":2005,"developer":"Pirate Games"},{"name":"Yoshinoya","year":2004,"developer":"Success Corp."},{"name":"Yotsunoha: A Journey of Sincerity","year":2008,"developer":"Haikuo Soft"},{"name":"Yourself!Fitness","year":2005,"developer":"Respondesign"},{"name":"Ys I・II: Eternal Story","year":2003,"developer":"Nihon Falcom Corp."},{"name":"Ys III: Wanderers from Ys","year":2005,"developer":"Taito Corporation"},{"name":"Ys IV: Mask of the Sun - A New Theory","year":2005,"developer":"Arc System Works Co., Ltd."},{"name":"Ys V: Lost Kefin, Kingdom of Sand","year":2006,"developer":"Access co., ltd."},{"name":"Ys VI: The Ark of Napishtim","year":2005,"developer":"Nihon Falcom Corp."},{"name":"Yu Yu Hakusho: Ghost Files - Dark Tournament","year":2004,"developer":"Digital Fiction Inc."},{"name":"Yu-Gi-Oh! GX: Tag Force","year":2007,"developer":"Konami Computer Entertainment Japan, Inc."},{"name":"Yu-Gi-Oh!: Capsule Monster Coliseum","year":2004,"developer":"Konami Computer Entertainment Japan, Inc."},{"name":"Yu-Gi-Oh!: The Duelists of the Roses","year":2001,"developer":"Konami Computer Entertainment Japan, Inc."},{"name":"Yukigatari: Renewal-ban","year":2005,"developer":"Takuyo Co., Ltd."},{"name":"Yumemi Hakusho: Second Dream","year":2008,"developer":"PrincessSoft"},{"name":"Yumemishi","year":2006,"developer":"H℃"}]